cronjob_scanner/__init__.py
cronjob_scanner/cron_collector.py
cronjob_scanner-0.5.dist-info/LICENSE
cronjob_scanner-0.5.dist-info/METADATA
cronjob_scanner-0.5.dist-info/WHEEL
cronjob_scanner-0.5.dist-info/entry_points.txt
cronjob_scanner-0.5.dist-info/top_level.txt
cronjob_scanner-0.5.dist-info/RECORD
