Metadata-Version: 2.1
Name: cronjob-scanner
Version: 0.5
License-File: LICENSE
Requires-Dist: requests
